datacommons_client/README.md
datacommons_client/__init__.py
datacommons_client/client.py
datacommons_client/endpoints/__init__.py
datacommons_client/endpoints/base.py
datacommons_client/endpoints/node.py
datacommons_client/endpoints/observation.py
datacommons_client/endpoints/payloads.py
datacommons_client/endpoints/resolve.py
datacommons_client/endpoints/response.py
datacommons_client/models/__init__.py
datacommons_client/models/base.py
datacommons_client/models/node.py
datacommons_client/models/observation.py
datacommons_client/models/resolve.py
datacommons_client/tests/README.MD
datacommons_client/tests/test_client.py
datacommons_client/tests/test_context.py
datacommons_client/tests/test_dataframes.py
datacommons_client/tests/test_decorators.py
datacommons_client/tests/test_names.py
datacommons_client/tests/test_utils.py
datacommons_client/tests/endpoints/test_base.py
datacommons_client/tests/endpoints/test_error_handling.py
datacommons_client/tests/endpoints/test_node_endpoint.py
datacommons_client/tests/endpoints/test_observation_endpoint.py
datacommons_client/tests/endpoints/test_payloads.py
datacommons_client/tests/endpoints/test_request_handling.py
datacommons_client/tests/endpoints/test_resolve_endpoint.py
datacommons_client/tests/endpoints/test_response.py
datacommons_client/tests/models/test_node_models.py
datacommons_client/tests/models/test_observation_models.py
datacommons_client/tests/models/test_resolve_models.py
datacommons_client/tests/utils/test_graph.py
datacommons_client/utils/__init__.py
datacommons_client/utils/context.py
datacommons_client/utils/data_processing.py
datacommons_client/utils/dataframes.py
datacommons_client/utils/decorators.py
datacommons_client/utils/error_handling.py
datacommons_client/utils/graph.py
datacommons_client/utils/names.py
datacommons_client/utils/request_handling.py
datacommons_client-2.1.6.dist-info/METADATA
datacommons_client-2.1.6.dist-info/WHEEL
datacommons_client-2.1.6.dist-info/licenses/LICENSE
datacommons_client-2.1.6.dist-info/RECORD
