Metadata-Version: 2.4
Name: datacommons-client
Version: 2.1.6
Summary: A library to access Data Commons Python API.
Project-URL: Homepage, https://github.com/datacommonsorg/api-python
Author-email: "datacommons.org" <support@datacommons.org>, "one.org" <data@one.org>
Maintainer-email: "datacommons.org" <support@datacommons.org>
License: 
License-File: LICENSE
Keywords: api,data,data commons,development
Classifier: Intended Audience :: Developers
Classifier: License :: OSI Approved :: Apache Software License
Classifier: Programming Language :: Python
Classifier: Programming Language :: Python :: 3.10
Classifier: Programming Language :: Python :: 3.11
Classifier: Programming Language :: Python :: 3.12
Classifier: Programming Language :: Python :: 3.13
Classifier: Programming Language :: Python :: Implementation :: CPython
Classifier: Topic :: Software Development
Requires-Python: >=3.10
Requires-Dist: pydantic>=2.11
Requires-Dist: requests>=2.32
Requires-Dist: typing-extensions
Provides-Extra: dev
Requires-Dist: hatch; extra == 'dev'
Requires-Dist: isort; extra == 'dev'
Requires-Dist: mock; extra == 'dev'
Requires-Dist: pytest; extra == 'dev'
Requires-Dist: yapf; extra == 'dev'
Provides-Extra: pandas
Requires-Dist: pandas; extra == 'pandas'
